pyleapy.py
pyleapy-0.0.4.dist-info/LICENSE
pyleapy-0.0.4.dist-info/METADATA
pyleapy-0.0.4.dist-info/WHEEL
pyleapy-0.0.4.dist-info/top_level.txt
pyleapy-0.0.4.dist-info/RECORD
