Metadata-Version: 2.1
Name: pyleapy
Version: 0.0.4
Summary: A simple python module to check whether a year is Leap year or not
Home-page: https://github.com/aru-jo/pyleapy
Author: Aravind Jyothi
Author-email: demievent@gmail.com
License: UNKNOWN
Download-URL: https://github.com/aru-jo/pyleapy/archive/0.0.4.tar.gz
Keywords: LEAP,YEAR,CHECK
Platform: UNKNOWN
